plugin_tools/__init__.py
plugin_tools/__main__.py
plugin_tools/constants.py
plugin_tools/main.py
plugin_tools/manifest.py
plugin_tools/package.py
plugin_tools/utils.py
Plugin_Tools-0.1.0.dist-info/LICENSE
Plugin_Tools-0.1.0.dist-info/METADATA
Plugin_Tools-0.1.0.dist-info/WHEEL
Plugin_Tools-0.1.0.dist-info/entry_points.txt
Plugin_Tools-0.1.0.dist-info/top_level.txt
Plugin_Tools-0.1.0.dist-info/RECORD
